{
  "bar_chart": {
    "title": "Bar Chart",
    "img": "/img/barChart.JPG",
    "url": "/gallery/barChart.html",
    "adapters": [
      {
        "name": "Vega-Lite",
        "code": "/examples/barChart-vl.html"
      },
      {
        "name": "Vega",
        "code": "/examples/barChart-v.html"
      },
      {
        "name": "ObservablePlot",
        "code": "/examples/barChart-op.html"
      }
    ]
  },
  "line_chart": {
    "title": "Line Chart",
    "img": "/img/lineChart.JPG",
    "url": "/gallery/lineChart.html",
    "adapters": [
      {
        "name": "Vega-Lite",
        "code": "/examples/lineChart-vl.html"
      },
      {
        "name": "Vega",
        "code": "/examples/lineChart-v.html"
      },
      {
        "name": "ObservablePlot",
        "code": "/examples/lineChart-op.html"
      }
    ]
  },
  "scatterplot": {
    "title": "Scatterplot",
    "img": "/img/scatterplot.JPG",
    "url": "/gallery/scatterplot.html",
    "adapters": [
      {
        "name": "Vega-Lite",
        "code": "/examples/scatterplot-vl.html"
      },
      {
        "name": "Vega",
        "code": "/examples/scatterplot-v.html"
      },
      {
        "name": "ObservablePlot",
        "code": "/examples/scatterplot-op.html"
      }
    ]
  },
  "multi_series_line_chart": {
    "title": "Multi-Series Line Chart",
    "img": "/img/multiSeriesLineChart.JPG",
    "url": "/gallery/multiSeriesLine.html",
    "adapters": [
      {
        "name": "Vega-Lite",
        "code": "/examples/multiSeriesChart-vl.html"
      },
      {
        "name": "Vega",
        "code": "/examples/multiSeriesChart-v.html"
      },
      {
        "name": "ObservablePlot",
        "code": "/examples/multiSeriesChart-op.html"
      }
    ]
  },
  "stacked_bar_chart": {
    "title": "Stacked Bar Chart",
    "img": "/img/stackedBarChart.JPG",
    "url": "/gallery/stackedBar.html",
    "adapters": [
      {
        "name": "Vega-Lite",
        "code": "/examples/stackedBar-vl.html"
      },
      {
        "name": "Vega",
        "code": "/examples/stackedBar-v.html"
      },
      {
        "name": "ObservablePlot",
        "code": "/examples/stackedBar-op.html"
      }
    ]
  },
  "faceted_chart": {
    "title": "Faceted Chart",
    "img": "/img/facetedChart.JPG",
    "url": "/gallery/facet.html",
    "adapters": [
      {
        "name": "Vega-Lite",
        "code": "/examples/facetedChart-vl.html"
      },
      {
        "name": "Vega",
        "code": "/examples/facetedChart-v.html"
      },
      {
        "name": "ObservablePlot",
        "code": "/examples/facetedChart-op.html"
      }
    ]
  },
  "layered_chart": {
    "title": "Layered Chart",
    "url": "/gallery/layer.html",
    "adapters": [
      {
        "name": "Vega-Lite",
        "code": "/examples/layeredChart-vl.html"
      }
    ]
  },
  "concat_chart": {
    "title": "Concatenated Chart",
    "url": "/gallery/concat.html",
    "adapters": [
      {
        "name": "Vega-Lite",
        "code": "/examples/concatChart-vl.html"
      }
    ]
  },
  "aggregate_bar_chart": {
    "title": "Aggregate Bar Chart",
    "url": "/gallery/aggregateBarChart.html",
    "adapters": [
      {
        "name": "Vega-Lite",
        "code": "/examples/aggregateBarChart-vl.html"
      }
    ]
  },
  "grouped_bar_chart": {
    "title": "Grouped Bar Chart",
    "url": "/gallery/groupedBarChart.html",
    "adapters": [
      {
        "name": "Vega-Lite",
        "code": "/examples/groupedBarChart-vl.html"
      }
    ]
  },
  "population_pyramid": {
    "title": "Population Pyramid",
    "url": "/gallery/populationPyramid.html",
    "adapters": [
      {
        "name": "Vega-Lite",
        "code": "/examples/populationPyramid-vl.html"
      }
    ]
  },
  "histogram": {
    "title": "Histogram",
    "url": "/gallery/histogram.html",
    "adapters": [
      {
        "name": "Vega-Lite",
        "code": "/examples/histogram-vl.html"
      }
    ]
  },
  "wilkinson_dot_plot": {
    "title": "Wilkinson Dot Plot",
    "url": "/gallery/wilkinsonDotPlot.html",
    "development_only": true,
    "adapters": [
      {
        "name": "Vega-Lite",
        "code": "/examples/wilkinsonDotPlot-vl.html"
      }
    ]
  },
  "density_plot": {
    "title": "Density Plot",
    "url": "/gallery/densityPlot.html",
    "development_only": true,
    "adapters": [
      {
        "name": "Vega-Lite",
        "code": "/examples/densityPlot-vl.html"
      }
    ]
  },
  "stacked_density_plot": {
    "title": "Stacked Density Plot",
    "url": "/gallery/stackedDensityPlot.html",
    "development_only": true,
    "adapters": [
      {
        "name": "Vega-Lite",
        "code": "/examples/stackedDensityPlot-vl.html"
      }
    ]
  },
  "isotype_dot_plot": {
    "title": "Isotype Dot Plot",
    "url": "/gallery/isotypeDotPlot.html",
    "development_only": true,
    "adapters": [
      {
        "name": "Vega-Lite",
        "code": "/examples/isotypeDotPlot-vl.html"
      }
    ]
  },
  "strip_plot": {
    "title": "Strip Plot",
    "url": "/gallery/stripPlot.html",
    "adapters": [
      {
        "name": "Vega-Lite",
        "code": "/examples/stripPlot-vl.html"
      }
    ]
  },
  "area_chart": {
    "title": "Area Chart",
    "url": "/gallery/areaChart.html",
    "adapters": [
      {
        "name": "Vega-Lite",
        "code": "/examples/areaChart-vl.html"
      }
    ]
  },
  "stacked_area_chart": {
    "title": "Stacked Area Chart",
    "url": "/gallery/stackedAreaChart.html",
    "adapters": [
      {
        "name": "Vega-Lite",
        "code": "/examples/stackedAreaChart-vl.html"
      }
    ]
  },
  "steamgraph": {
    "title": "Steamgraph",
    "url": "/gallery/steamgraph.html",
    "adapters": [
      {
        "name": "Vega-Lite",
        "code": "/examples/steamgraph-vl.html"
      }
    ]
  },
  "heatmap": {
    "title": "Heatmap",
    "url": "/gallery/heatmap.html",
    "adapters": [
      {
        "name": "Vega-Lite",
        "code": "/examples/heatmap-vl.html"
      }
    ]
  },
  "lasagna_plot": {
    "title": "Lasagna Plot",
    "url": "/gallery/lasagnaPlot.html",
    "adapters": [
      {
        "name": "Vega-Lite",
        "code": "/examples/lasagnaPlot-vl.html"
      }
    ]
  },
  "pie_chart": {
    "title": "Pie Chart",
    "url": "/gallery/pieChart.html",
    "development_only": true,
    "adapters": [
      {
        "name": "Vega-Lite",
        "code": "/examples/pieChart-vl.html"
      }
    ]
  }
}